sdh/redis/__init__.py
sdh/redis/connection.py
sdh/redis/pool.py
sdh_redis-1.0.0.dist-info/licenses/LICENSE
sdh_redis-1.0.0.dist-info/METADATA
sdh_redis-1.0.0.dist-info/WHEEL
sdh_redis-1.0.0.dist-info/top_level.txt
sdh_redis-1.0.0.dist-info/RECORD
