Metadata-Version: 2.4
Name: sdh.redis
Version: 1.0.0
Summary: Django redis wrapper.
Author-email: Viacheslav Vic Bukhantsov <vic.bukhantsov@gmail.com>
Maintainer-email: Viacheslav Vic Bukhantsov <vic.bukhantsov@gmail.com>
License-Expression: BSD-2-Clause
Project-URL: Repository, https://github.com/sdh-global/sdh-redis
Classifier: Development Status :: 5 - Production/Stable
Classifier: Intended Audience :: Developers
Classifier: Framework :: Django
Classifier: Operating System :: OS Independent
Classifier: Programming Language :: Python
Classifier: Programming Language :: Python :: 3
Classifier: Programming Language :: Python :: 3.8
Classifier: Programming Language :: Python :: 3.9
Classifier: Topic :: Internet :: WWW/HTTP :: Dynamic Content
Classifier: Topic :: Software Development
Classifier: Topic :: Software Development :: Libraries
Requires-Python: >=3.8
License-File: LICENSE
Requires-Dist: Django>=4.2
Requires-Dist: redis>=5.2.1
Dynamic: license-file
